Metadata-Version: 1.1
Name: monitoring-plugins-apparmor
Version: 1.0.1
Summary: This script checks the state AppArmor status and profiles.
Home-page: https://github.com/mgrzybek/monitoring-plugins-apparmor
Author: Mathieu Grzybek
Author-email: mathieu@grzybek.fr
License: GPLv3
Download-URL: https://github.com/mgrzybek/monitoring-plugins-apparmor/archive/1.0.1.tar.gz
Keywords: monitoring check apparmor activity
Platform: UNKNOWN
Classifier: Development Status :: 5 - Production/Stable
Classifier: Topic :: Utilities
Classifier: Environment :: Console
Classifier: License :: OSI Approved :: GNU General Public License v3 or later (GPLv3+)
